mroudai_django_tenants-0.1.0.dist-info/licenses/LICENSE
tenants/__init__.py
tenants/admin.py
tenants/apps.py
tenants/middleware.py
tenants/models.py
tenants/permissions.py
tenants/resolution.py
tenants/roles.py
tenants/services.py
tenants/migrations/0001_initial.py
tenants/migrations/__init__.py
tenants/tests/__init__.py
tenants/tests/settings.py
tenants/tests/test_models.py
tenants/tests/test_resolution.py
tenants/tests/test_roles.py
tenants/tests/test_services.py
tenants/tests/urls.py
mroudai_django_tenants-0.1.0.dist-info/METADATA
mroudai_django_tenants-0.1.0.dist-info/WHEEL
mroudai_django_tenants-0.1.0.dist-info/top_level.txt
mroudai_django_tenants-0.1.0.dist-info/RECORD
